{"nodes": [{"id": "src_lib_sync_field_mapping_test_ts", "label": "field-mapping.test.ts", "file_type": "code", "source_file": "src\\lib\\sync\\field-mapping.test.ts", "source_location": "L1"}], "edges": [{"source": "src_lib_sync_field_mapping_test_ts", "target": "vitest", "relation": "imports_from", "confidence": "EXTRACTED", "source_file": "src\\lib\\sync\\field-mapping.test.ts", "source_location": "L1", "weight": 1.0}, {"source": "src_lib_sync_field_mapping_test_ts", "target": "src_lib_sync_field_mapping", "relation": "imports_from", "confidence": "EXTRACTED", "source_file": "src\\lib\\sync\\field-mapping.test.ts", "source_location": "L2", "weight": 1.0}], "raw_calls": []}