{"nodes": [{"id": "src_components_sync_syncstatusicon_tsx", "label": "SyncStatusIcon.tsx", "file_type": "code", "source_file": "src\\components\\sync\\SyncStatusIcon.tsx", "source_location": "L1"}, {"id": "syncstatusicon_syncstatusicon", "label": "SyncStatusIcon()", "file_type": "code", "source_file": "src\\components\\sync\\SyncStatusIcon.tsx", "source_location": "L8"}], "edges": [{"source": "src_components_sync_syncstatusicon_tsx", "target": "lucide_react", "relation": "imports_from", "confidence": "EXTRACTED", "source_file": "src\\components\\sync\\SyncStatusIcon.tsx", "source_location": "L3", "weight": 1.0}, {"source": "src_components_sync_syncstatusicon_tsx", "target": "usesync", "relation": "imports_from", "confidence": "EXTRACTED", "source_file": "src\\components\\sync\\SyncStatusIcon.tsx", "source_location": "L4", "weight": 1.0}, {"source": "src_components_sync_syncstatusicon_tsx", "target": "button", "relation": "imports_from", "confidence": "EXTRACTED", "source_file": "src\\components\\sync\\SyncStatusIcon.tsx", "source_location": "L5", "weight": 1.0}, {"source": "src_components_sync_syncstatusicon_tsx", "target": "tooltip", "relation": "imports_from", "confidence": "EXTRACTED", "source_file": "src\\components\\sync\\SyncStatusIcon.tsx", "source_location": "L6", "weight": 1.0}, {"source": "src_components_sync_syncstatusicon_tsx", "target": "syncstatusicon_syncstatusicon", "relation": "contains", "confidence": "EXTRACTED", "source_file": "src\\components\\sync\\SyncStatusIcon.tsx", "source_location": "L8", "weight": 1.0}], "raw_calls": [{"caller_nid": "syncstatusicon_syncstatusicon", "callee": "useSync", "source_file": "src\\components\\sync\\SyncStatusIcon.tsx", "source_location": "L9"}, {"caller_nid": "syncstatusicon_syncstatusicon", "callee": "toLocaleTimeString", "source_file": "src\\components\\sync\\SyncStatusIcon.tsx", "source_location": "L45"}]}